FODLego/Analysis.py
FODLego/BFOD.py
FODLego/Bond.py
FODLego/ElementaryClasses.py
FODLego/FFOD.py
FODLego/FOD.py
FODLego/FOD_Print.py
FODLego/Funcs.py
FODLego/MolecularSet.py
FODLego/Molecule.py
FODLego/Predict.py
FODLego/Shells.py
FODLego/__init__.py
FODLego/__main__.py
FODLego/elements2.0
FODLego/experiments.py
FODLego/globaldata.py
FODLego/graphing.py
FODLego/pubc.py
fodlego-0.3.11.dist-info/METADATA
fodlego-0.3.11.dist-info/WHEEL
fodlego-0.3.11.dist-info/entry_points.txt
fodlego-0.3.11.dist-info/licenses/LICENSE
fodlego-0.3.11.dist-info/RECORD
