Metadata-Version: 2.3
Name: FODLego
Version: 0.3.11
Summary: This package creates initial FODs for molecules with atoms up to the third row in th periodic table.
Project-URL: Homepage, https://github.com/nerffan1/FODLego
Project-URL: Issues, https://github.com/nerffan1/FODLego/issues
Project-URL: Documentation, https://nerffan1.github.io/FLOSICDOC/Reference/Generation.html
Project-URL: Website, https://www.flosic.org/
Author-email: Angel-Emilio Villegas Sanchez <ville2a@cmich.edu>
License-File: LICENSE
Keywords: DFT,FLOSIC,FODs,Fermi-Lowdin,SIC,SIE,self-interaction
Classifier: License :: OSI Approved :: GNU General Public License v3 (GPLv3)
Classifier: Operating System :: OS Independent
Classifier: Programming Language :: Python :: 3
Requires-Python: >=3.8
Requires-Dist: matplotlib
Requires-Dist: numpy
Requires-Dist: rdkit
Requires-Dist: scipy
